certbot_dns_exonet/__init__.py
certbot_dns_exonet/authenticators/__init__.py
certbot_dns_exonet/authenticators/exonet_authenticator.py
certbot_dns_exonet/clients/__init__.py
certbot_dns_exonet/clients/exonet_client.py
certbot_dns_exonet/services/__init__.py
certbot_dns_exonet/services/dns_service.py
certbot_dns_exonet-4.0.0.dist-info/LICENSE
certbot_dns_exonet-4.0.0.dist-info/METADATA
certbot_dns_exonet-4.0.0.dist-info/WHEEL
certbot_dns_exonet-4.0.0.dist-info/entry_points.txt
certbot_dns_exonet-4.0.0.dist-info/RECORD
