Metadata-Version: 2.3
Name: certbot-dns-exonet
Version: 4.0.0
Summary: Exonet DNS Authenticator plugin for Certbot
Home-page: https://github.com/exonet/certbot-dns-exonet
License: MIT
Author: Exonet
Author-email: development@exonet.nl
Requires-Python: >=3.9,<3.14
Classifier: Development Status :: 5 - Production/Stable
Classifier: Environment :: Plugins
Classifier: Intended Audience :: System Administrators
Classifier: License :: OSI Approved :: MIT License
Classifier: Operating System :: POSIX :: Linux
Classifier: Programming Language :: Python
Classifier: Programming Language :: Python :: 3
Classifier: Programming Language :: Python :: 3.9
Classifier: Programming Language :: Python :: 3.10
Classifier: Programming Language :: Python :: 3.11
Classifier: Programming Language :: Python :: 3.12
Classifier: Programming Language :: Python :: 3.13
Classifier: Topic :: Internet :: WWW/HTTP
Classifier: Topic :: Security
Classifier: Topic :: System :: Installation/Setup
Classifier: Topic :: System :: Networking
Classifier: Topic :: System :: Systems Administration
Classifier: Topic :: Utilities
Requires-Dist: acme (>=2.5.0,<3.0.0)
Requires-Dist: certbot (>=2.5.0,<3.0.0)
Requires-Dist: exonetapi (>=4.0.0,<5.0.0)
Requires-Dist: requests (>=2.28.2,<3.0.0)
Requires-Dist: tldextract (>=3.4,<5.0)
Project-URL: Documentation, https://github.com/exonet/certbot-dns-exonet
Project-URL: Repository, https://github.com/exonet/certbot-dns-exonet
